flourish/__init__.py
flourish/command_line.py
flourish/dirtrie.py
flourish/examples.py
flourish/filters.py
flourish/generators.py
flourish/helpers.py
flourish/lib.py
flourish/paginator.py
flourish/sectileloader.py
flourish/skeletons.py
flourish/source.py
flourish/sourcelist.py
flourish/url.py
flourish/version.py
flourish/blueprint/__init__.py
flourish/blueprint/blueprint_template.html
flourish/blueprint/blueprint_toolbar.html
flourish/generators/__init__.py
flourish/generators/atom.py
flourish/generators/base.py
flourish/generators/calendar.py
flourish/generators/csv.py
flourish/generators/mixins.py
flourish/generators/sass.py
flourish-0.10.3.dist-info/LICENCE
flourish-0.10.3.dist-info/LICENSE
flourish-0.10.3.dist-info/METADATA
flourish-0.10.3.dist-info/WHEEL
flourish-0.10.3.dist-info/entry_points.txt
flourish-0.10.3.dist-info/top_level.txt
flourish-0.10.3.dist-info/RECORD
