Metadata-Version: 2.1
Name: flourish
Version: 0.10.3
Summary: Static website generator
Home-page: https://github.com/norm/flourish
Author: Mark Norman Francis
Author-email: norm@201created.com
License: MIT
Platform: UNKNOWN
Classifier: Development Status :: 3 - Alpha
Classifier: Intended Audience :: Developers
Classifier: License :: OSI Approved :: MIT License
Classifier: Programming Language :: Python :: 3
Classifier: Topic :: Software Development :: Build Tools
Classifier: Topic :: Software Development :: Code Generators
Classifier: Topic :: Text Processing :: Markup :: HTML
Classifier: Topic :: Internet :: WWW/HTTP :: Site Management
Requires-Python: >=3.6
Requires-Dist: boto3
Requires-Dist: Flask
Requires-Dist: Jinja2 (>=2.9)
Requires-Dist: markdown2
Requires-Dist: feedgen
Requires-Dist: toml
Requires-Dist: libsass
Requires-Dist: sectile (>=0.3.5)
Requires-Dist: jsonpickle
Requires-Dist: importlib-resources ; python_version <= "3.9"
